win64_process_toolkit/__init__.py
win64_process_toolkit/__internal/Win64ProcToolkit.dll
win64_process_toolkit/__internal/native_lib.py
win64_process_toolkit/__pyinstaller/__init__.py
win64_process_toolkit/__pyinstaller/hook-win64_process_toolkit.py
win64_process_toolkit-1.1.0.dist-info/METADATA
win64_process_toolkit-1.1.0.dist-info/WHEEL
win64_process_toolkit-1.1.0.dist-info/entry_points.txt
win64_process_toolkit-1.1.0.dist-info/top_level.txt
win64_process_toolkit-1.1.0.dist-info/RECORD
