Metadata-Version: 2.4
Name: win64_process_toolkit
Version: 1.1.0
Summary: Process Toolkit for Windows x86_64 & arm64
Author: GlacieTeam
License: MPL-2.0
Classifier: Programming Language :: Python :: 3
Classifier: Operating System :: Microsoft :: Windows
Requires-Python: >=3
